[
  {
    "title": "APOIE",
    "actions": [
      {
        "text": "Cadastre um município",
        "to": "https://censo.ok.org.br/"
      },
      { "text": "Nossas Metas", "to": "/apoie", "fragment": "nossas-metas" },
      { "text": "Quem apoia", "to": "/apoie", "fragment": "quem-apoia" },
      { "text": "Envie sua sugestão", "to": "/sugestao" }
    ]
  },
  {
    "title": "TECNOLOGIA",
    "actions": [
      {
        "text": "Documentação",
        "to": "/tecnologia",
        "fragment": "documentacao"
      },
      {
        "text": "Contribua com código",
        "to": "/tecnologia",
        "fragment": "contribua"
      },
      { "text": "Relatórios", "to": "/tecnologia", "fragment": "relatorios" }
    ]
  },
  {
    "title": "SOBRE",
    "actions": [
      { "text": "História", "to": "/sobre", "fragment": "historia" },
      {
        "text": "Casos de sucesso",
        "to": "/sobre",
        "fragment": "casos-de-sucesso"
      },
      { "text": "Quem somos", "to": "sobre#casos-de-sucesso" },
      {
        "text": "Política de privacidade",
        "to": "/privacidade"
      }
    ]
  }
]
